{"baidu-map.md":"039e6cfe","begin_base.md":"46cc32c6","begin_install.md":"89e554cb","begin_third-party.md":"6f6145c8","begin_use.md":"41b6b39c","bmaplib_curve-line.md":"dd3bdc51","bmaplib_heatmap.md":"82993676","bmaplib_index.md":"e9a625a8","bmaplib_lushu.md":"1e93a9a4","bmaplib_marker-clusterer.md":"90518716","control_cheju.md":"ab7a0cbb","control_city-list.md":"75baefe8","control_control.md":"69019842","control_copyright.md":"35af7d17","control_geolocation.md":"05390be8","control_map-type.md":"59ec56af","control_navigation.md":"e04f2dec","control_overview.md":"04b0b588","control_panorama.md":"ecd79bd8","control_scale.md":"0afc23a8","guid_painting.md":"fb3a3b57","hole_index.md":"9b113622","index.md":"2ecf6fb1","layer_tile.md":"435f88e7","layer_traffic.md":"d4e70635","menu_menu-item.md":"f6bd9235","menu_menu.md":"c5310708","other_auto-complete.md":"7d7bac3c","other_boundary.md":"bee77096","overlay_circle.md":"1b153660","overlay_ground.md":"6e7b94ad","overlay_info-window.md":"e58ed55b","overlay_label.md":"12b782fb","overlay_marker.md":"860b5406","overlay_overlay.md":"20a3ca58","overlay_point-collection.md":"af018952","overlay_polygon.md":"0e801db2","overlay_polyline.md":"acf1b0e2","search_bus.md":"ade5c676","search_driving.md":"2d6d0510","search_local-search.md":"63b0df49","search_transit.md":"50a21ea1","search_walking.md":"85ae5d4a","shuangxiang.md":"88ea7b75"}
